msp/__init__.py
msp/inference.py
msp-2023.10.6.post1.dist-info/LICENSE
msp-2023.10.6.post1.dist-info/METADATA
msp-2023.10.6.post1.dist-info/WHEEL
msp-2023.10.6.post1.dist-info/top_level.txt
msp-2023.10.6.post1.dist-info/RECORD
