Metadata-Version: 2.1
Name: msp
Version: 2023.10.6.post1
Summary: MSP SDK
Home-page: https://github.com/sktaiflow/msp-sdk
Author: sktdmi
Author-email: mls@sktai.io
Classifier: Programming Language :: Python :: 3
Classifier: License :: OSI Approved :: MIT License
Classifier: Operating System :: OS Independent
Requires-Python: >=3.8
License-File: LICENSE
Requires-Dist: aiohttp ==3.8.4
Requires-Dist: requests ==2.30.0
Requires-Dist: urllib3 ==1.26.7
Requires-Dist: opentelemetry-api ==1.13.0
Requires-Dist: opentelemetry-sdk ==1.13.0
Requires-Dist: opentelemetry-instrumentation-requests ==0.34b0
Requires-Dist: opentelemetry-exporter-otlp ==1.13.0
Requires-Dist: opentelemetry-instrumentation-aiohttp-client ==0.34b0
Requires-Dist: opentelemetry-instrumentation-urllib3 ==0.34b0
